enocean/__init__.py
enocean/consolelogger.py
enocean/decorators.py
enocean/utils.py
enocean/communicators/__init__.py
enocean/communicators/communicator.py
enocean/communicators/serialcommunicator.py
enocean/communicators/tcpcommunicator.py
enocean/communicators/utils.py
enocean/protocol/EEP.xml
enocean/protocol/__init__.py
enocean/protocol/constants.py
enocean/protocol/crc8.py
enocean/protocol/eep.py
enocean/protocol/packet.py
py_enocean-0.53.0.data/scripts/enocean_example.py
py_enocean-0.53.0.dist-info/LICENSE
py_enocean-0.53.0.dist-info/METADATA
py_enocean-0.53.0.dist-info/WHEEL
py_enocean-0.53.0.dist-info/top_level.txt
py_enocean-0.53.0.dist-info/RECORD
