Metadata-Version: 2.1
Name: py-enocean
Version: 0.53.0
Summary: EnOcean serial protocol implementation
Home-page: https://github.com/bakkerv/py-enocean
Author: Vincent Bakker
Author-email: mail@bakkerv.nl
License: UNKNOWN
Platform: UNKNOWN
Requires-Dist: enum-compat (>=0.0.2)
Requires-Dist: pyserial (>=3.0)
Requires-Dist: beautifulsoup4 (>=4.3.2)
